[
	{
		"__TYPE__": "SharedSliceContent",
		"variation": "default",
		"primary": {
			"heading": {
				"__TYPE__": "StructuredTextContent",
				"value": [
					{
						"type": "heading2",
						"content": {
							"text": "Random Gallery",
							"spans": []
						},
						"direction": "ltr"
					}
				]
			},
			"subtext": {
				"__TYPE__": "StructuredTextContent",
				"value": [
					{
						"type": "paragraph",
						"content": {
							"text": "Fugiat sit cillum dolor fugiat aute qui officia eiusmod dolor."
						}
					}
				]
			}
		},
		"items": [
			{
				"__TYPE__": "GroupItemContent",
				"value": [
					[
						"image",
						{
							"origin": {
								"id": "main",
								"url": "https://images.unsplash.com/photo-1587905069134-008460d7a636",
								"width": 3935,
								"height": 5894
							},
							"url": "https://images.unsplash.com/photo-1587905069134-008460d7a636?rect=0%2C0%2C3935%2C5894&w=2000&h=2996",
							"width": 2000,
							"height": 2996,
							"edit": {
								"zoom": 1,
								"crop": {
									"x": 0,
									"y": 0
								},
								"background": "transparent"
							},
							"credits": null,
							"alt": null,
							"__TYPE__": "ImageContent",
							"thumbnails": {}
						}
					],
					[
						"title",
						{
							"__TYPE__": "StructuredTextContent",
							"value": [
								{
									"type": "paragraph",
									"content": {
										"text": "Title for this image",
										"spans": []
									},
									"direction": "ltr"
								}
							]
						}
					],
					[
						"description",
						{
							"__TYPE__": "StructuredTextContent",
							"value": [
								{
									"type": "paragraph",
									"content": {
										"text": "Pariatur ullamco cupidatat excepteur in cupidatat elit quis incididunt ipsum reprehenderit in. Consectetur et nostrud in id proident Lorem cupidatat voluptate commodo id."
									}
								}
							]
						}
					]
				]
			},
			{
				"__TYPE__": "GroupItemContent",
				"value": [
					[
						"image",
						{
							"url": "https://images.unsplash.com/photo-1546548970-71785318a17b?crop=entropy&cs=srgb&fm=jpg&ixid=M3wzMzc0NjN8MHwxfHNlYXJjaHwxfHxjaXRydXMlMjBmcnVpdHxlbnwwfHx8fDE3MTg2MzUzOTJ8MA&ixlib=rb-4.0.3&q=85&rect=0%2C0%2C3104%2C4656&w=2000&h=3000",
							"alt": "flat lay photography of sliced pomegranate, lime, and lemon",
							"origin": {
								"id": "7r1HxvVC7AY",
								"url": "https://images.unsplash.com/photo-1546548970-71785318a17b?crop=entropy&cs=srgb&fm=jpg&ixid=M3wzMzc0NjN8MHwxfHNlYXJjaHwxfHxjaXRydXMlMjBmcnVpdHxlbnwwfHx8fDE3MTg2MzUzOTJ8MA&ixlib=rb-4.0.3&q=85",
								"width": 3104,
								"height": 4656
							},
							"width": 2000,
							"height": 3000,
							"edit": {
								"background": "transparent",
								"zoom": 1,
								"crop": {
									"x": 0,
									"y": 0
								}
							},
							"credits": null,
							"__TYPE__": "ImageContent",
							"thumbnails": {}
						}
					]
				]
			},
			{
				"__TYPE__": "GroupItemContent",
				"value": [
					[
						"image",
						{
							"url": "https://images.unsplash.com/photo-1577234286642-fc512a5f8f11?crop=entropy&cs=srgb&fm=jpg&ixid=M3wzMzc0NjN8MHwxfHNlYXJjaHwyfHxjaXRydXMlMjBmcnVpdHxlbnwwfHx8fDE3MTg2MzUzOTJ8MA&ixlib=rb-4.0.3&q=85&rect=0%2C0%2C3024%2C4032&w=2000&h=2667",
							"alt": "sliced grapefruits",
							"origin": {
								"id": "ezSFnAFi9hY",
								"url": "https://images.unsplash.com/photo-1577234286642-fc512a5f8f11?crop=entropy&cs=srgb&fm=jpg&ixid=M3wzMzc0NjN8MHwxfHNlYXJjaHwyfHxjaXRydXMlMjBmcnVpdHxlbnwwfHx8fDE3MTg2MzUzOTJ8MA&ixlib=rb-4.0.3&q=85",
								"width": 3024,
								"height": 4032
							},
							"width": 2000,
							"height": 2667,
							"edit": {
								"background": "transparent",
								"zoom": 1,
								"crop": {
									"x": 0,
									"y": 0
								}
							},
							"credits": null,
							"__TYPE__": "ImageContent",
							"thumbnails": {}
						}
					]
				]
			},
			{
				"__TYPE__": "GroupItemContent",
				"value": [
					[
						"image",
						{
							"url": "https://images.unsplash.com/photo-1511688878353-3a2f5be94cd7?crop=entropy&cs=srgb&fm=jpg&ixid=M3wzMzc0NjN8MHwxfHNlYXJjaHwzfHxjaXRydXMlMjBmcnVpdHxlbnwwfHx8fDE3MTg2MzUzOTJ8MA&ixlib=rb-4.0.3&q=85&rect=0%2C0%2C3709%2C5563&w=2000&h=3000",
							"alt": "assorted sliced citrus fruits on brown wooden chopping board",
							"origin": {
								"id": "1CsaVdwfIew",
								"url": "https://images.unsplash.com/photo-1511688878353-3a2f5be94cd7?crop=entropy&cs=srgb&fm=jpg&ixid=M3wzMzc0NjN8MHwxfHNlYXJjaHwzfHxjaXRydXMlMjBmcnVpdHxlbnwwfHx8fDE3MTg2MzUzOTJ8MA&ixlib=rb-4.0.3&q=85",
								"width": 3709,
								"height": 5563
							},
							"width": 2000,
							"height": 3000,
							"edit": {
								"background": "transparent",
								"zoom": 1,
								"crop": {
									"x": 0,
									"y": 0
								}
							},
							"credits": null,
							"__TYPE__": "ImageContent",
							"thumbnails": {}
						}
					]
				]
			},
			{
				"__TYPE__": "GroupItemContent",
				"value": [
					[
						"image",
						{
							"url": "https://images.unsplash.com/photo-1517260739337-6799d239ce83?crop=entropy&cs=srgb&fm=jpg&ixid=M3wzMzc0NjN8MHwxfHNlYXJjaHw1fHxjaXRydXMlMjBmcnVpdHxlbnwwfHx8fDE3MTg2MzUzOTJ8MA&ixlib=rb-4.0.3&q=85&rect=0%2C0%2C5760%2C3839&w=2000&h=1333",
							"alt": "sliced fruit on white surface",
							"origin": {
								"id": "YSA1IRkGAsg",
								"url": "https://images.unsplash.com/photo-1517260739337-6799d239ce83?crop=entropy&cs=srgb&fm=jpg&ixid=M3wzMzc0NjN8MHwxfHNlYXJjaHw1fHxjaXRydXMlMjBmcnVpdHxlbnwwfHx8fDE3MTg2MzUzOTJ8MA&ixlib=rb-4.0.3&q=85",
								"width": 5760,
								"height": 3840
							},
							"width": 2000,
							"height": 1333,
							"edit": {
								"background": "transparent",
								"zoom": 1,
								"crop": {
									"x": 0,
									"y": 0
								}
							},
							"credits": null,
							"__TYPE__": "ImageContent",
							"thumbnails": {}
						}
					]
				]
			},
			{
				"__TYPE__": "GroupItemContent",
				"value": [
					[
						"image",
						{
							"url": "https://images.unsplash.com/photo-1597714026720-8f74c62310ba?crop=entropy&cs=srgb&fm=jpg&ixid=M3wzMzc0NjN8MHwxfHNlYXJjaHwxMHx8Y2l0cnVzJTIwZnJ1aXR8ZW58MHx8fHwxNzE4NjM1MzkyfDA&ixlib=rb-4.0.3&q=85&rect=0%2C0%2C5688%2C3791&w=2000&h=1333",
							"alt": "orange fruits under blue sky during daytime",
							"origin": {
								"id": "eaOjEz8746k",
								"url": "https://images.unsplash.com/photo-1597714026720-8f74c62310ba?crop=entropy&cs=srgb&fm=jpg&ixid=M3wzMzc0NjN8MHwxfHNlYXJjaHwxMHx8Y2l0cnVzJTIwZnJ1aXR8ZW58MHx8fHwxNzE4NjM1MzkyfDA&ixlib=rb-4.0.3&q=85",
								"width": 5688,
								"height": 3792
							},
							"width": 2000,
							"height": 1333,
							"edit": {
								"background": "transparent",
								"zoom": 1,
								"crop": {
									"x": 0,
									"y": 0
								}
							},
							"credits": null,
							"__TYPE__": "ImageContent",
							"thumbnails": {}
						}
					]
				]
			}
		]
	}
]